pygameextra/__init__.py
pygameextra/build/scripts-3.8/pygameextra-pong
pygameextra/dist/pygameextra_pong-0.0.0-py3.8.egg
pygameextra/examples/pong/font.ttf
pygameextra/examples/pong/pygameextra-pong
pygameextra/files/slider.png
pygameextra/pygameextra_pong.egg-info/PKG-INFO
pygameextra/pygameextra_pong.egg-info/SOURCES.txt
pygameextra/pygameextra_pong.egg-info/dependency_links.txt
pygameextra/pygameextra_pong.egg-info/top_level.txt
pygameextra/setup.py
pygameextra-1.6.3.999.dist-info/WHEEL
pygameextra-1.6.3.999.dist-info/METADATA
pygameextra-1.6.3.999.dist-info/RECORD
