Metadata-Version: 2.1
Name: pygameextra
Version: 1.6.3.999
Summary: pygame extra is a mask for pygame, you can easily make complex games and or apps with much less lines then you would of before, Pygame Extra makes coding easier
License: BSD-3-Clause
Author: RedstoneHair
Requires-Python: >=3.5,<4.0
Classifier: License :: OSI Approved :: BSD License
Classifier: Programming Language :: Python :: 3
Classifier: Programming Language :: Python :: 3.5
Classifier: Programming Language :: Python :: 3.6
Classifier: Programming Language :: Python :: 3.7
Classifier: Programming Language :: Python :: 3.8
Classifier: Programming Language :: Python :: 3.9
Requires-Dist: pygame (>=1.9.6,<2.0.0)
